ohlc/__init__.py
ohlc/__main__.py
ohlc/cli.py
ohlc/colors.py
ohlc/input.py
ohlc/random.py
ohlc/types.py
ohlc/candles/__init__.py
ohlc/candles/app.py
ohlc/candles/chart.py
ohlc/candles/fills.py
ohlc/candles/turtle.py
ohlc-0.1.13.dist-info/LICENSE.txt
ohlc-0.1.13.dist-info/METADATA
ohlc-0.1.13.dist-info/WHEEL
ohlc-0.1.13.dist-info/entry_points.txt
ohlc-0.1.13.dist-info/top_level.txt
ohlc-0.1.13.dist-info/RECORD
