Metadata-Version: 2.1
Name: ohlc
Version: 0.1.13
Summary: Ohlc: Types + Tools for Open-High-Low-Close Values
Home-page: https://github.com/ubunatic/ohlc
Author: Uwe Jugel
Author-email: uwe.jugel@gmail.com
License: MIT
Download-URL: https://github.com/ubunatic/ohlc/tarball/master
Project-URL: Documentation, https://github.com/ubunatic/ohlc
Project-URL: Bug Reports, https://github.com/ubunatic/ohlc/issues
Project-URL: Funding, https://github.com/ubunatic/ohlc
Project-URL: Say Thanks!, https://saythanks.io/to/ubunatic
Project-URL: Source, https://github.com/ubunatic/ohlc
Keywords: ohlc data types finance bitcoin ccxt candlesticks charts widgets graph
Platform: UNKNOWN
Classifier: Development Status :: 3 - Alpha
Classifier: Environment :: Console :: Curses
Classifier: Topic :: Utilities
Classifier: Topic :: Software Development :: Libraries
Classifier: Topic :: Software Development :: Widget Sets
Classifier: Topic :: Scientific/Engineering :: Visualization
Classifier: Topic :: Office/Business :: Financial :: Investment
Classifier: Intended Audience :: Financial and Insurance Industry
Classifier: Intended Audience :: Developers
Classifier: License :: OSI Approved :: MIT License
Classifier: Programming Language :: Python
Classifier: Programming Language :: Python :: 3
Classifier: Programming Language :: Python :: 3.5
Classifier: Programming Language :: Python :: 3.6
License-File: LICENSE.txt
Requires-Dist: urwid
Requires-Dist: typing
Requires-Dist: drawille
Requires-Dist: widdy
